django_happenings_update-0.4.4.dist-info/DESCRIPTION.rst
django_happenings_update-0.4.4.dist-info/METADATA
django_happenings_update-0.4.4.dist-info/RECORD
django_happenings_update-0.4.4.dist-info/WHEEL
django_happenings_update-0.4.4.dist-info/metadata.json
django_happenings_update-0.4.4.dist-info/top_level.txt
happenings/__init__.py
happenings/admin.py
happenings/managers.py
happenings/models.py
happenings/urls.py
happenings/views.py
happenings/migrations/0001_initial.py
happenings/migrations/0002_auto_20180525_1554.py
happenings/migrations/__init__.py
happenings/south_migrations/0001_initial.py
happenings/south_migrations/0002_auto__add_cancellation.py
happenings/south_migrations/__init__.py
happenings/static/happenings/css/calendar.css
happenings/static/happenings/js/calendar.js
happenings/templates/happenings/base.html
happenings/templates/happenings/event_day_list.html
happenings/templates/happenings/event_detail.html
happenings/templates/happenings/event_month_list.html
happenings/templates/happenings/middle.html
happenings/templates/happenings/partials/event_list.html
happenings/templates/happenings/partials/happening_events.html
happenings/templates/happenings/partials/upcoming_events.html
happenings/templates/happenings/partials/calendar/day_cell.html
happenings/templates/happenings/partials/calendar/day_noday_cell.html
happenings/templates/happenings/partials/calendar/mini_day_cell.html
happenings/templates/happenings/partials/calendar/mini_popover.html
happenings/templates/happenings/partials/calendar/month_table.html
happenings/templates/happenings/partials/calendar/popover.html
happenings/templatetags/__init__.py
happenings/templatetags/happenings_tags.py
happenings/templatetags/weekday.py
happenings/utils/__init__.py
happenings/utils/calendars.py
happenings/utils/common.py
happenings/utils/displays.py
happenings/utils/handlers.py
happenings/utils/mixins.py
happenings/utils/next_event.py
happenings/utils/upcoming.py
