Metadata-Version: 2.0
Name: django-happenings-update
Version: 0.4.4
Summary: A simple event calendar app for Django.
Home-page: https://github.com/imposeren/django-happenings
Author: Yaroslav Klyuyev
Author-email: imposeren@gmail.com
License: BSD License
Platform: UNKNOWN
Classifier: Environment :: Web Environment
Classifier: Framework :: Django
Classifier: Development Status :: 4 - Beta
Classifier: Intended Audience :: Developers
Classifier: License :: OSI Approved :: BSD License
Classifier: Operating System :: OS Independent
Classifier: Programming Language :: Python
Classifier: Topic :: Internet :: WWW/HTTP
Classifier: Topic :: Internet :: WWW/HTTP :: Dynamic Content
Classifier: Topic :: Software Development :: Libraries :: Python Modules
Requires-Dist: django (>=1.11)
Requires-Dist: pytz
Requires-Dist: six (<2.0,>=1.9)
